{
  "region": "us-west-2",
  "configuration": "Debug",
  "framework": "net5.0",
  "self-contained": false,
  "application": "BookstoreBackend",
  "environment": "BookstoreBackend-admindev",
  "enable-xray": false,
  "enhanced-health-type": "basic",
  "additional-options": "\"aws:autoscaling:launchconfiguration,SecurityGroups\"=\"sg-04236c837495c77b9,sg-075d858dbd4d56826\";\"aws:ec2:vpc,Subnets\"=\"subnet-0df045fa2622c7fb9\"",
  "solution-stack": "64bit Windows Server Core 2019 v2.7.0 running IIS 10.0",
  "environment-type": "SingleInstance",
  "cname": "bookstorebackend-admindev",
  "instance-type": "t3a.medium",
  "key-pair": "",
  "instance-profile": "BookstoreCdkStackVersion27-BookstoreInstanceProfileVersion27-1BUBA8HQ3Z78Z",
  "service-role": "aws-elasticbeanstalk-service-role",
  "proxy-server": "none",
  "profile": "default",
  "health-check-url": "/",
  "iis-website": "Default Web Site",
  "app-path": "/"
}